[{"disabled":false,"group":null,"selected":false,"text":"Buxgalteriya hisobi va audit (tarmoqlar bo‘yicha)","value":"60410103"},{"disabled":false,"group":null,"selected":false,"text":"Ma'lumotlar ilmi(Data Science)","value":"60612200"},{"disabled":false,"group":null,"selected":false,"text":"Moliya va moliyaviy texnologiyalar","value":"60410400"},{"disabled":false,"group":null,"selected":false,"text":"Raqamli iqtisodiyot (tarmoqlar va sohalar bo‘yicha)","value":"60310501"},{"disabled":false,"group":null,"selected":false,"text":"Soliqlar va soliqqa tortish (faoliyat turlari bo‘yicha)","value":"60410200"}]