[{"disabled":false,"group":null,"selected":false,"text":"Biologiya","value":"60110900"},{"disabled":false,"group":null,"selected":false,"text":"Boshlang‘ich ta’lim","value":"60110500"},{"disabled":false,"group":null,"selected":false,"text":"Boshlang‘ich ta’lim-Ishtixon tumani","value":"60110500216"},{"disabled":false,"group":null,"selected":false,"text":"Boshlang‘ich ta’lim-Kattaqo'rg'on tumani","value":"60110500218"},{"disabled":false,"group":null,"selected":false,"text":"Boshlang‘ich ta’lim-Nurobod tumani","value":"60110500220"},{"disabled":false,"group":null,"selected":false,"text":"Boshlang‘ich ta’lim-Payariq tumani","value":"60110500224"},{"disabled":false,"group":null,"selected":false,"text":"Boshlang‘ich ta’lim-Qo'shrabot tumani","value":"60110500225"},{"disabled":false,"group":null,"selected":false,"text":"Boshlang‘ich ta’lim-Urgut tumani","value":"60110500228"},{"disabled":false,"group":null,"selected":false,"text":"Fizika va astronomiya","value":"60110700"},{"disabled":false,"group":null,"selected":false,"text":"Geografiya va iqtisodiy bilim asoslari","value":"60111000"},{"disabled":false,"group":null,"selected":false,"text":"Jismoniy madaniyat","value":"60112200"},{"disabled":false,"group":null,"selected":false,"text":"Kimyo","value":"60110800"},{"disabled":false,"group":null,"selected":false,"text":"Maktabgacha ta’lim","value":"60110200"},{"disabled":false,"group":null,"selected":false,"text":"Maktabgacha va boshlang‘ich ta'limda jismoniy tarbiya va sport","value":"60111900"},{"disabled":false,"group":null,"selected":false,"text":"Matematika va informatika","value":"60110600"},{"disabled":false,"group":null,"selected":false,"text":"Matematika va informatika-Kattaqo'rg'on tumani","value":"60110600218"},{"disabled":false,"group":null,"selected":false,"text":"Matematika va informatika-Nurobod tumani","value":"60110600220"},{"disabled":false,"group":null,"selected":false,"text":"Matematika va informatika-Payariq tumani","value":"60110600224"},{"disabled":false,"group":null,"selected":false,"text":"Matematika va informatika-Qo'shrabot tumani","value":"60110600225"},{"disabled":false,"group":null,"selected":false,"text":"Matematika va informatika-Urgut tumani","value":"60110600228"},{"disabled":false,"group":null,"selected":false,"text":"Musiqa ta'limi","value":"60111300"},{"disabled":false,"group":null,"selected":false,"text":"O‘zbek tili va adabiyoti","value":"60111400"},{"disabled":false,"group":null,"selected":false,"text":"O‘zga tilli guruhlarda rus tili (o‘zbek guruhlari uchun)","value":"60111701"},{"disabled":false,"group":null,"selected":false,"text":"O‘zga tilli guruhlarda rus tili (o‘zbek guruhlari uchun)-Ishtixon tumani","value":"60111701216"},{"disabled":false,"group":null,"selected":false,"text":"O‘zga tilli guruhlarda rus tili (o‘zbek guruhlari uchun)-Kattaqo'rg'on tumani","value":"60111701218"},{"disabled":false,"group":null,"selected":false,"text":"O‘zga tilli guruhlarda rus tili (o‘zbek guruhlari uchun)-Narpay tumani","value":"60111701219"},{"disabled":false,"group":null,"selected":false,"text":"O‘zga tilli guruhlarda rus tili (o‘zbek guruhlari uchun)-Paxtachi tumani","value":"60111701223"},{"disabled":false,"group":null,"selected":false,"text":"O‘zga tilli guruhlarda rus tili (o‘zbek guruhlari uchun)-Payariq tumani","value":"60111701224"},{"disabled":false,"group":null,"selected":false,"text":"O‘zga tilli guruhlarda rus tili (o‘zbek guruhlari uchun)-Qo'shrabot tumani","value":"60111701225"},{"disabled":false,"group":null,"selected":false,"text":"O‘zga tilli guruhlarda rus tili (o‘zbek guruhlari uchun)-Urgut tumani","value":"60111701228"},{"disabled":false,"group":null,"selected":false,"text":"Sport faoliyati: futbol","value":"61010342"},{"disabled":false,"group":null,"selected":false,"text":"Sport faoliyati: kurash","value":"61010320"},{"disabled":false,"group":null,"selected":false,"text":"Sport faoliyati: qo‘l to‘pi","value":"61010321"},{"disabled":false,"group":null,"selected":false,"text":"Sport faoliyati: voleybol","value":"61010311"},{"disabled":false,"group":null,"selected":false,"text":"Tarix","value":"60111100"},{"disabled":false,"group":null,"selected":false,"text":"Tasviriy san'at va muhandislik grafikasi  ","value":"60111200"},{"disabled":false,"group":null,"selected":false,"text":"Texnologik ta’lim","value":"60112300"},{"disabled":false,"group":null,"selected":false,"text":"Xorijiy til va adabiyoti: ingliz tili","value":"60111802"}]